{
  "Title":"Nebraska ATRI VIZ",
  "CountyFile":"ZoneShape.json",
  "ZoneFile":"ZoneShape.json",
  "Icon":"RSG.ico",
  "Logo":"ndot_logo_black.png",
  "NavbarTitle":"ATRIVIZ",
  "LinkURL":"https://dot.nebraska.gov",
  "CenterMap": [41.460011, -99.791661],
  "FrontPageTitle": "Nebraska DOT",
  "FrontPageGraphic": "ndot_logo_white.png",
  "scenarios":{
    "ATRI": {
      "title":"- ATRI Processing",
      "visualizations": {
        "Sunburst": [],
        "3DMap": [],
        "GroupedCharts": [],
        "TimeUse": [],
        "RadarCharts": [],
        "BarMap": [],
        "Scatter":[],
        "POIMap": [],
        "Chord": [{"name":"Chord","config":"Default","file":"ChordData.csv"}]
      }
    }
  },

  "RadarCharts":{
    "Default": {
      "NumberColsRadar": 4,
      "IndependentScale": [
        ""
      ],
      "ConvertAxesToPercent": true
    }
  },
  "GroupedCharts":{
    "Default": {
      "NumberColsGrouped": 1,
      "SwapLegendByDefault": true,
      "ShowAsPercentByDefault": true,
      "ShowAsVerticalByDefault": false,
      "StackAllChartsByDefault": false,
      "ChartWidthOverride": []
    }
  },
  "3DMap":{
    "Default" : {
      "ShowPeriodsAsDropdown": false,
      "DataHasPeriods": true,
      "ZoneFile": []
    }
  },
  "Chord": {
    "Default": {
      "ZoneFilterFile": "cocs.csv",
      "LabelSize": "14",
      "LegendText": "Truck Flows"
    }
    }
}
